agent.py
cli.py
tool_functions.py
tools.py
nexus_ai_agent-1.0.2.dist-info/licenses/LICENSE
nexus_ai_agent-1.0.2.dist-info/METADATA
nexus_ai_agent-1.0.2.dist-info/WHEEL
nexus_ai_agent-1.0.2.dist-info/entry_points.txt
nexus_ai_agent-1.0.2.dist-info/top_level.txt
nexus_ai_agent-1.0.2.dist-info/RECORD
