Metadata-Version: 2.4
Name: nexus-ai-agent
Version: 1.0.2
Summary: Intelligent Agentic File Assistant powered by Claude
Home-page: https://github.com/Remote-Skills/nexus
Author: Chiheb Nabil
Author-email: Chiheb Nabil <hi@remoteskills.io>
Maintainer-email: Chiheb Nabil <hi@remoteskills.io>
License-Expression: MIT
Project-URL: Homepage, https://github.com/Remote-Skills/nexus
Project-URL: Documentation, https://github.com/Remote-Skills/nexus#readme
Project-URL: Repository, https://github.com/Remote-Skills/nexus
Project-URL: Bug Tracker, https://github.com/Remote-Skills/nexus/issues
Keywords: ai,agent,claude,anthropic,automation,agentic,file-operations
Classifier: Development Status :: 4 - Beta
Classifier: Intended Audience :: Developers
Classifier: Topic :: Software Development :: Libraries :: Application Frameworks
Classifier: Topic :: Scientific/Engineering :: Artificial Intelligence
Classifier: Programming Language :: Python :: 3
Classifier: Programming Language :: Python :: 3.8
Classifier: Programming Language :: Python :: 3.9
Classifier: Programming Language :: Python :: 3.10
Classifier: Programming Language :: Python :: 3.11
Classifier: Programming Language :: Python :: 3.12
Requires-Python: >=3.8
License-File: LICENSE
Requires-Dist: anthropic>=0.25.0
Requires-Dist: python-dotenv>=1.0.0
Requires-Dist: rich>=13.0.0
Provides-Extra: dev
Requires-Dist: pytest>=7.0.0; extra == "dev"
Requires-Dist: pytest-cov>=4.0.0; extra == "dev"
Requires-Dist: black>=23.0.0; extra == "dev"
Requires-Dist: flake8>=6.0.0; extra == "dev"
Requires-Dist: mypy>=1.0.0; extra == "dev"
Dynamic: author
Dynamic: home-page
Dynamic: license-file
Dynamic: requires-python
